fourutils/FilterParser.py
fourutils/IdenticonGenerator.py
fourutils/ServerSentEvent.py
fourutils/__init__.py
fourutils/asynchronous/Periodic.py
fourutils/asynchronous/__init__.py
fourutils/base36.py
fourutils/flask/RedisSessionInterface.py
fourutils/flask/ReverseProxied.py
fourutils/flask/__init__.py
fourutils/flask/msgpack.py
fourutils/flask/testing/UserTestContext.py
fourutils/flask/testing/__init__.py
fourutils/ldap/AuthLDAP.py
fourutils/ldap/__init__.py
fourutils/log.py
fourutils/monkeypatch.py
fourutils/sqla/UserConfigManager.py
fourutils/sqla/__init__.py
fourutils/sqla/mixins/__init__.py
fourutils/sqla/mixins/audit.py
fourutils/sqla/types/JSONEncodedDict.py
fourutils/sqla/types/__init__.py
fourutils/webnotifications/PushPackageBuilder.py
fourutils/webnotifications/__init__.py
fourutils-0.2.1.dist-info/LICENSE
fourutils-0.2.1.dist-info/WHEEL
fourutils-0.2.1.dist-info/METADATA
fourutils-0.2.1.dist-info/RECORD
